fake_ua/__init__.py
fake_ua-0.0.3.dist-info/METADATA
fake_ua-0.0.3.dist-info/WHEEL
fake_ua-0.0.3.dist-info/top_level.txt
fake_ua-0.0.3.dist-info/RECORD
